<?xml version="1.0" encoding="UTF-8"?>
<objects serializationModel="Studio.01.10.00">
    <object class="Event" id="{bc1a5afe-b3d8-4e43-83a8-b2e6a91823f3}">
        <property name="name">
            <value>SFX_GameStart</value>
        </property>
        <property name="outputFormat">
            <value>2</value>
        </property>
        <relationship name="folder">
            <destination>{e8ca1fe7-164a-41be-9c9c-ba592b8f83ad}</destination>
        </relationship>
        <relationship name="mixer">
            <destination>{766a4ef5-c579-47fd-a891-065ba8bed46f}</destination>
        </relationship>
        <relationship name="masterTrack">
            <destination>{8c8e5e17-fa2b-4e94-b0f7-c04430749bd0}</destination>
        </relationship>
        <relationship name="mixerInput">
            <destination>{8a8d846c-03bf-4281-8635-6623ad1e8e56}</destination>
        </relationship>
        <relationship name="automatableProperties">
            <destination>{16574a7e-780f-425d-b715-16e1de12bcbe}</destination>
        </relationship>
        <relationship name="markerTracks">
            <destination>{108f2db2-6e63-42b1-9ced-3475592d91a3}</destination>
        </relationship>
        <relationship name="groupTracks">
            <destination>{dadc0c8f-3267-444a-94e8-5e34c66b1643}</destination>
        </relationship>
        <relationship name="timeline">
            <destination>{1c75b001-20e3-4214-8228-a79edb59aa36}</destination>
        </relationship>
    </object>
    <object class="EventMixer" id="{766a4ef5-c579-47fd-a891-065ba8bed46f}">
        <relationship name="masterBus">
            <destination>{aee5a076-de93-4c6b-9a5c-2b6d3c3e8618}</destination>
        </relationship>
    </object>
    <object class="MasterTrack" id="{8c8e5e17-fa2b-4e94-b0f7-c04430749bd0}">
        <relationship name="mixerGroup">
            <destination>{aee5a076-de93-4c6b-9a5c-2b6d3c3e8618}</destination>
        </relationship>
    </object>
    <object class="MixerInput" id="{8a8d846c-03bf-4281-8635-6623ad1e8e56}">
        <relationship name="effectChain">
            <destination>{17cd496a-4301-4129-849a-6d9f253fd003}</destination>
        </relationship>
        <relationship name="panner">
            <destination>{a92a1971-4e13-42a1-a4c4-521297d2214c}</destination>
        </relationship>
        <relationship name="output">
            <destination>{a3ff7962-f3fd-4e6f-8e4a-cd97c96e8681}</destination>
        </relationship>
    </object>
    <object class="EventAutomatableProperties" id="{16574a7e-780f-425d-b715-16e1de12bcbe}"/>
    <object class="MarkerTrack" id="{108f2db2-6e63-42b1-9ced-3475592d91a3}"/>
    <object class="GroupTrack" id="{dadc0c8f-3267-444a-94e8-5e34c66b1643}">
        <relationship name="mixerGroup">
            <destination>{33a671fb-31fa-4ecd-b86d-157a5050aecd}</destination>
        </relationship>
    </object>
    <object class="Timeline" id="{1c75b001-20e3-4214-8228-a79edb59aa36}"/>
    <object class="EventMixerMaster" id="{aee5a076-de93-4c6b-9a5c-2b6d3c3e8618}">
        <relationship name="effectChain">
            <destination>{7ade811d-0edc-43fb-b993-45dff9ca25c8}</destination>
        </relationship>
        <relationship name="panner">
            <destination>{0227c0dc-3793-4a6e-a438-5bca4d58d1d6}</destination>
        </relationship>
        <relationship name="mixer">
            <destination>{766a4ef5-c579-47fd-a891-065ba8bed46f}</destination>
        </relationship>
    </object>
    <object class="MixerBusEffectChain" id="{17cd496a-4301-4129-849a-6d9f253fd003}">
        <relationship name="effects">
            <destination>{9395383a-c81c-473c-94b8-40a41fcf54d1}</destination>
        </relationship>
    </object>
    <object class="MixerBusPanner" id="{a92a1971-4e13-42a1-a4c4-521297d2214c}"/>
    <object class="EventMixerGroup" id="{33a671fb-31fa-4ecd-b86d-157a5050aecd}">
        <property name="name">
            <value>Audio 1</value>
        </property>
        <relationship name="effectChain">
            <destination>{a5224aa3-1e62-433e-9a9a-29e8671b0498}</destination>
        </relationship>
        <relationship name="panner">
            <destination>{3b4047ad-906f-4549-879f-c752f66fdc3d}</destination>
        </relationship>
        <relationship name="output">
            <destination>{aee5a076-de93-4c6b-9a5c-2b6d3c3e8618}</destination>
        </relationship>
    </object>
    <object class="MixerBusEffectChain" id="{7ade811d-0edc-43fb-b993-45dff9ca25c8}">
        <relationship name="effects">
            <destination>{0402c739-459f-4bb3-9142-f0ac3f1d03c1}</destination>
            <destination>{298ecb87-4054-42d5-aaed-c41220cba8b7}</destination>
        </relationship>
    </object>
    <object class="MixerBusPanner" id="{0227c0dc-3793-4a6e-a438-5bca4d58d1d6}"/>
    <object class="MixerBusFader" id="{9395383a-c81c-473c-94b8-40a41fcf54d1}"/>
    <object class="MixerBusEffectChain" id="{a5224aa3-1e62-433e-9a9a-29e8671b0498}">
        <relationship name="effects">
            <destination>{706c3825-51cb-4cd6-943f-f6816b3ddfbc}</destination>
        </relationship>
    </object>
    <object class="MixerBusPanner" id="{3b4047ad-906f-4549-879f-c752f66fdc3d}"/>
    <object class="MixerBusFader" id="{0402c739-459f-4bb3-9142-f0ac3f1d03c1}"/>
    <object class="SpatialiserEffect" id="{298ecb87-4054-42d5-aaed-c41220cba8b7}"/>
    <object class="MixerBusFader" id="{706c3825-51cb-4cd6-943f-f6816b3ddfbc}"/>
</objects>
