<?xml version="1.0" encoding="UTF-8"?>
<objects serializationModel="Studio.01.10.00">
    <object class="EncodingSetting" id="{2a7453d4-d708-4265-8c8e-5dd886dd4a04}">
        <property name="encodingFormat">
            <value>3</value>
        </property>
        <property name="quality">
            <value>37</value>
        </property>
        <property name="loadingMode">
            <value>1</value>
        </property>
        <relationship name="platform">
            <destination>{f9142a14-9d5e-4196-a5f4-6777dd3eb500}</destination>
        </relationship>
        <relationship name="encodable">
            <destination>{571ae36a-1bf4-4cd9-b99e-c6c2f00d0e14}</destination>
        </relationship>
    </object>
</objects>
