<?xml version="1.0" encoding="UTF-8"?>
<objects serializationModel="Studio.01.10.00">
    <object class="EncodingSetting" id="{4b0ff332-0edc-41db-b7bd-ea8760be13fd}">
        <property name="encodingFormat">
            <value>3</value>
        </property>
        <property name="quality">
            <value>37</value>
        </property>
        <property name="loadingMode">
            <value>1</value>
        </property>
        <relationship name="platform">
            <destination>{f9142a14-9d5e-4196-a5f4-6777dd3eb500}</destination>
        </relationship>
        <relationship name="encodable">
            <destination>{6c55b3e6-84b5-4c9a-bc0f-8665217d76ca}</destination>
        </relationship>
    </object>
</objects>
